django_otp_messagebird-0.2.2.dist-info/licenses/LICENSE
otp_messagebird/__init__.py
otp_messagebird/admin.py
otp_messagebird/conf.py
otp_messagebird/models.py
otp_messagebird/tests.py
otp_messagebird/migrations/0001_initial.py
otp_messagebird/migrations/0002_sidechanneldevice.py
otp_messagebird/migrations/0003_messagebirdvoicedevice.py
otp_messagebird/migrations/0004_messagebirdvoicedevice_language.py
otp_messagebird/migrations/0005_throttling.py
otp_messagebird/migrations/__init__.py
django_otp_messagebird-0.2.2.dist-info/METADATA
django_otp_messagebird-0.2.2.dist-info/WHEEL
django_otp_messagebird-0.2.2.dist-info/top_level.txt
django_otp_messagebird-0.2.2.dist-info/RECORD
